Metadata-Version: 1.0
Name: heol-torso
Version: 1.0.2
Summary: Heol Software Library
Home-page: https://github.com/Heolrobotics/Heol-torso
Author: Alexandre Le Falher, Florian RUEN
Author-email: florian.ruen@gmail.com
License: GNU GENERAL PUBLIC LICENSE Version 3
Platform: UNKNOWN
